treebeard/__init__.py
treebeard/admin.py
treebeard/al_tree.py
treebeard/exceptions.py
treebeard/forms.py
treebeard/models.py
treebeard/mp_tree.py
treebeard/ns_tree.py
treebeard/numconv.py
treebeard/locale/de/LC_MESSAGES/django.mo
treebeard/locale/de/LC_MESSAGES/django.po
treebeard/locale/de/LC_MESSAGES/djangojs.mo
treebeard/locale/de/LC_MESSAGES/djangojs.po
treebeard/locale/es/LC_MESSAGES/django.mo
treebeard/locale/es/LC_MESSAGES/django.po
treebeard/locale/es/LC_MESSAGES/djangojs.mo
treebeard/locale/es/LC_MESSAGES/djangojs.po
treebeard/locale/nl/LC_MESSAGES/django.mo
treebeard/locale/nl/LC_MESSAGES/django.po
treebeard/locale/nl/LC_MESSAGES/djangojs.mo
treebeard/locale/nl/LC_MESSAGES/djangojs.po
treebeard/locale/pl/LC_MESSAGES/django.mo
treebeard/locale/pl/LC_MESSAGES/django.po
treebeard/locale/ru/LC_MESSAGES/django.mo
treebeard/locale/ru/LC_MESSAGES/django.po
treebeard/locale/ru/LC_MESSAGES/djangojs.mo
treebeard/locale/ru/LC_MESSAGES/djangojs.po
treebeard/static/treebeard/expand-collapse.png
treebeard/static/treebeard/jquery-ui-1.8.5.custom.min.js
treebeard/static/treebeard/treebeard-admin.css
treebeard/static/treebeard/treebeard-admin.js
treebeard/templates/admin/tree_change_list.html
treebeard/templates/admin/tree_change_list_results.html
treebeard/templates/admin/tree_list.html
treebeard/templates/admin/tree_list_results.html
treebeard/templatetags/__init__.py
treebeard/templatetags/admin_tree.py
treebeard/templatetags/admin_tree_list.py
treebeard/tests/__init__.py
treebeard/tests/admin.py
treebeard/tests/conftest.py
treebeard/tests/models.py
treebeard/tests/settings.py
treebeard/tests/test_treebeard.py
treebeard/tests/urls.py
treebeard/tests/jenkins/rm_workspace_coverage.py
treebeard/tests/jenkins/toxhelper.py
django_treebeard_rvanlaar-4.3.dist-info/LICENSE
django_treebeard_rvanlaar-4.3.dist-info/METADATA
django_treebeard_rvanlaar-4.3.dist-info/WHEEL
django_treebeard_rvanlaar-4.3.dist-info/top_level.txt
django_treebeard_rvanlaar-4.3.dist-info/RECORD
